LICENSE
README.md
pyproject.toml
setup.cfg
setup.py
dazer/Classifier.py
dazer/Regressor.py
dazer/Subsampler.py
dazer/__init__.py
dazer/defaults.py
dazer/random_forest_utils.py
dazer/utils.py
dazer/wrappers.py
dazer.egg-info/PKG-INFO
dazer.egg-info/SOURCES.txt
dazer.egg-info/dependency_links.txt
dazer.egg-info/requires.txt
dazer.egg-info/top_level.txt
tests/test_Classifier.py
tests/test_Subsampler.py